TesterhomeWikiAppniumRumenjiaochengFix1/README.md
TesterhomeWikiAppniumRumenjiaochengFix1/__init__.py
TesterhomeWikiAppniumRumenjiaochengFix1/__main__.py
TesterhomeWikiAppniumRumenjiaochengFix1/file.epub
TesterhomeWikiAppniumRumenjiaochengFix1/index.html
TesterhomeWikiAppniumRumenjiaochengFix1/css/__init__.py
TesterhomeWikiAppniumRumenjiaochengFix1/css/annotations.css
TesterhomeWikiAppniumRumenjiaochengFix1/css/main.css
TesterhomeWikiAppniumRumenjiaochengFix1/css/normalize.css
TesterhomeWikiAppniumRumenjiaochengFix1/css/popup.css
TesterhomeWikiAppniumRumenjiaochengFix1/font/__init__.py
TesterhomeWikiAppniumRumenjiaochengFix1/font/fontello.eot
TesterhomeWikiAppniumRumenjiaochengFix1/font/fontello.svg
TesterhomeWikiAppniumRumenjiaochengFix1/font/fontello.ttf
TesterhomeWikiAppniumRumenjiaochengFix1/font/fontello.woff
TesterhomeWikiAppniumRumenjiaochengFix1/img/__init__.py
TesterhomeWikiAppniumRumenjiaochengFix1/img/annotator-glyph-sprite.png
TesterhomeWikiAppniumRumenjiaochengFix1/img/annotator-icon-sprite.png
TesterhomeWikiAppniumRumenjiaochengFix1/img/apple-touch-icon.png
TesterhomeWikiAppniumRumenjiaochengFix1/img/cancelfullscreen.png
TesterhomeWikiAppniumRumenjiaochengFix1/img/close.png
TesterhomeWikiAppniumRumenjiaochengFix1/img/fullscreen.png
TesterhomeWikiAppniumRumenjiaochengFix1/img/loader.gif
TesterhomeWikiAppniumRumenjiaochengFix1/img/menu-icon.png
TesterhomeWikiAppniumRumenjiaochengFix1/img/save.png
TesterhomeWikiAppniumRumenjiaochengFix1/img/saved.png
TesterhomeWikiAppniumRumenjiaochengFix1/img/settings-s.png
TesterhomeWikiAppniumRumenjiaochengFix1/img/settings.png
TesterhomeWikiAppniumRumenjiaochengFix1/img/star.png
TesterhomeWikiAppniumRumenjiaochengFix1/js/__init__.py
TesterhomeWikiAppniumRumenjiaochengFix1/js/epub.js
TesterhomeWikiAppniumRumenjiaochengFix1/js/epub.min.js
TesterhomeWikiAppniumRumenjiaochengFix1/js/epub.min.map
TesterhomeWikiAppniumRumenjiaochengFix1/js/hooks.min.js
TesterhomeWikiAppniumRumenjiaochengFix1/js/hooks.min.map
testerhome_wiki_appnium_rumenjiaocheng_fix1-2025.3.25.0.dist-info/METADATA
testerhome_wiki_appnium_rumenjiaocheng_fix1-2025.3.25.0.dist-info/WHEEL
testerhome_wiki_appnium_rumenjiaocheng_fix1-2025.3.25.0.dist-info/entry_points.txt
testerhome_wiki_appnium_rumenjiaocheng_fix1-2025.3.25.0.dist-info/top_level.txt
testerhome_wiki_appnium_rumenjiaocheng_fix1-2025.3.25.0.dist-info/RECORD
